grafana_dashboard/__init__.py
grafana_dashboard/dashboard.py
grafana_dashboard/model.py
grafana_dashboard_templater-1.0.3.dist-info/LICENSE
grafana_dashboard_templater-1.0.3.dist-info/METADATA
grafana_dashboard_templater-1.0.3.dist-info/WHEEL
grafana_dashboard_templater-1.0.3.dist-info/top_level.txt
grafana_dashboard_templater-1.0.3.dist-info/RECORD
