Metadata-Version: 2.1
Name: grafana-dashboard-templater
Version: 1.0.3
Summary: A Grafana dashboard templater
Home-page: https://github.com/ZPascal/grafana_dashboard_templater
Author: Pascal Zimmermann
Author-email: info@theiotstudio.com
Project-URL: Bug Tracker, https://github.com/ZPascal/grafana_dashboard_templater/issues
Classifier: Programming Language :: Python :: 3
Classifier: License :: OSI Approved
Classifier: Operating System :: OS Independent
Requires-Python: >=3.6
License-File: LICENSE
Requires-Dist: jinja2
